dmcontent/__init__.py
dmcontent/content_loader.py
dmcontent/converters.py
dmcontent/errors.py
dmcontent/formats.py
dmcontent/govuk_frontend.py
dmcontent/html.py
dmcontent/markdown.py
dmcontent/messages.py
dmcontent/metadata.py
dmcontent/py.typed
dmcontent/questions.py
dmcontent/utils.py
digitalmarketplace_content_loader-9.2.0.dist-info/LICENCE
digitalmarketplace_content_loader-9.2.0.dist-info/METADATA
digitalmarketplace_content_loader-9.2.0.dist-info/WHEEL
digitalmarketplace_content_loader-9.2.0.dist-info/top_level.txt
digitalmarketplace_content_loader-9.2.0.dist-info/RECORD
