Metadata-Version: 2.1
Name: digitalmarketplace-content-loader
Version: 9.2.0
Summary: Digital Marketplace Content Loader
Home-page: https://github.com/alphagov/digitalmarketplace-content-loader
Author: GDS Developers
License: MIT
Platform: UNKNOWN
Requires-Python: ~=3.8
Requires-Dist: Flask (<2.1,>=1.0)
Requires-Dist: Jinja2 (<3.1,>=2.10)
Requires-Dist: Markdown (<4.0.0,>=2.6.7)
Requires-Dist: PyYAML (<7.0,>=5.1.2)
Requires-Dist: inflection (<1.0.0,>=0.3.1)
Requires-Dist: digitalmarketplace-utils (>=59.0.0)
